swarm_to_sqlite/__init__.py
swarm_to_sqlite/cli.py
swarm_to_sqlite/utils.py
swarm_to_sqlite-0.3.4.dist-info/LICENSE
swarm_to_sqlite-0.3.4.dist-info/METADATA
swarm_to_sqlite-0.3.4.dist-info/WHEEL
swarm_to_sqlite-0.3.4.dist-info/entry_points.txt
swarm_to_sqlite-0.3.4.dist-info/top_level.txt
swarm_to_sqlite-0.3.4.dist-info/RECORD
