Metadata-Version: 2.1
Name: swarm-to-sqlite
Version: 0.3.4
Summary: Create a SQLite database containing your checkin history from Foursquare Swarm
Home-page: https://github.com/dogsheep/swarm-to-sqlite
Author: Simon Willison
License: Apache License, Version 2.0
Project-URL: Issues, https://github.com/dogsheep/swarm-to-sqlite/issues
Project-URL: CI, https://github.com/dogsheep/swarm-to-sqlite/actions
Project-URL: Changelog, https://github.com/dogsheep/swarm-to-sqlite/releases
License-File: LICENSE
Requires-Dist: sqlite-utils (>=3.3)
Requires-Dist: click
Requires-Dist: requests
Provides-Extra: test
Requires-Dist: pytest ; extra == 'test'
